{
  "providerId": "nicesite.so",
  "providerName": "nicesite",
  "serviceId": "hosting",
  "serviceName": "nicesite",
  "version": 1,
  "logoUrl": "https://ucarecdn.com/541766e8-3c80-41b2-b3ad-5a3c3da88806/nicesite_logo_circlecrop.png",
  "description": "Enables custom domain connection for hosting nicesite websites.",
  "records": [
    {
      "type":"A",
      "host":"@",
      "pointsTo":"75.2.60.5",
      "ttl": 300
    },
    {
      "type":"CNAME",
      "host":"www",
      "pointsTo": "@",
      "ttl": 300
    }
  ]
}
